pydentity_db_tortoise/__init__.py
pydentity_db_tortoise/fields.py
pydentity_db_tortoise/models/__init__.py
pydentity_db_tortoise/models/abstract.py
pydentity_db_tortoise/models/base.py
pydentity_db_tortoise/stores/__init__.py
pydentity_db_tortoise/stores/role_store.py
pydentity_db_tortoise/stores/user_store.py
pydentity_db_tortoise-0.1.3.dist-info/LICENSE
pydentity_db_tortoise-0.1.3.dist-info/METADATA
pydentity_db_tortoise-0.1.3.dist-info/WHEEL
pydentity_db_tortoise-0.1.3.dist-info/RECORD
