Metadata-Version: 2.1
Name: pydentity-db-tortoise
Version: 0.1.3
Summary: Database adapter for TortoiseORM.
Home-page: https://github.com/udachin077/pydentity-db-tortoise
License: MIT
Author: udachin077
Author-email: pypi.udachin@yandex.ru
Requires-Python: >=3.12,<4.0
Classifier: License :: OSI Approved :: MIT License
Classifier: Programming Language :: Python :: 3
Classifier: Programming Language :: Python :: 3.12
Requires-Dist: tortoise-orm (>=0.21.5,<0.22.0)
Project-URL: Repository, https://github.com/udachin077/pydentity-db-tortoise.git
